{
  "users": [
    {
      "id": 1,
      "name": "admin",
      "password": "dilligrout",
      "email": "admin@lagoon.com"
    }
  ],
  "patients": [
    {
      "name": "Kenpachi",
      "age": "45",
      "email": "zaraki@email.com",
      "phone": "08178019236",
      "ailments": "Murderous intent",
      "id": 1
    },
    {
      "name": "Antonin Dolohov",
      "age": "25",
      "email": "dolohov@gmail.com",
      "phone": "07023042432",
      "ailments": "wizadry",
      "id": 5
    },
    {
      "name": "Helen Mirren",
      "age": "54",
      "email": "helen@hollywood.com",
      "phone": "01-555-3245",
      "ailments": "amnesia, paranoia",
      "id": 7
    },
    {
      "name": "Samantha Wheeler",
      "age": "33",
      "email": "sam@psl.com",
      "phone": "01-772-9230",
      "ailments": "daddy issues",
      "id": 8
    },
    {
      "name": "Haz",
      "age": "39",
      "email": "dev_haz@email.com",
      "phone": "08178009955",
      "ailments": "anxiety,depression",
      "id": 10
    }
  ]
}